MANIFEST.in
README.md
idb.py
setup.cfg
setup.py
ipython_db.egg-info/PKG-INFO
ipython_db.egg-info/SOURCES.txt
ipython_db.egg-info/dependency_links.txt
ipython_db.egg-info/not-zip-safe
ipython_db.egg-info/requires.txt
ipython_db.egg-info/top_level.txt