Metadata-Version: 1.1
Name: ipython-db
Version: 1.0
Summary: Ipython db.py shell extension
Home-page: https://github.com/dongweiming/idb
Author: Dongweiming
Author-email: ciici123@gmail.com
License: MIT
Download-URL: https://github.com/dongweiming/idb/tarball/0.1
Keywords: database,ipython,shell,db.py
Platform: UNKNOWN
Classifier: Environment :: Console
Classifier: License :: OSI Approved :: MIT License
Classifier: Framework :: IPython
Classifier: Topic :: Database
Classifier: Topic :: Database :: Front-Ends
Classifier: Programming Language :: Python :: 2
